odoo/addons/website_sale_product_attribute_filter_visibility/README.rst
odoo/addons/website_sale_product_attribute_filter_visibility/__init__.py
odoo/addons/website_sale_product_attribute_filter_visibility/__manifest__.py
odoo/addons/website_sale_product_attribute_filter_visibility/controllers/__init__.py
odoo/addons/website_sale_product_attribute_filter_visibility/controllers/main.py
odoo/addons/website_sale_product_attribute_filter_visibility/data/demo.xml
odoo/addons/website_sale_product_attribute_filter_visibility/i18n/es.po
odoo/addons/website_sale_product_attribute_filter_visibility/i18n/website_sale_product_attribute_filter_visibility.pot
odoo/addons/website_sale_product_attribute_filter_visibility/models/__init__.py
odoo/addons/website_sale_product_attribute_filter_visibility/models/product_attribute.py
odoo/addons/website_sale_product_attribute_filter_visibility/readme/CONTRIBUTORS.rst
odoo/addons/website_sale_product_attribute_filter_visibility/readme/DESCRIPTION.rst
odoo/addons/website_sale_product_attribute_filter_visibility/readme/USAGE.rst
odoo/addons/website_sale_product_attribute_filter_visibility/static/description/icon.png
odoo/addons/website_sale_product_attribute_filter_visibility/static/description/index.html
odoo/addons/website_sale_product_attribute_filter_visibility/static/src/js/website_sale_product_attribute_filter_visibility_tour.js
odoo/addons/website_sale_product_attribute_filter_visibility/tests/__init__.py
odoo/addons/website_sale_product_attribute_filter_visibility/tests/test_attribute_filter_visibility.py
odoo/addons/website_sale_product_attribute_filter_visibility/views/assets.xml
odoo/addons/website_sale_product_attribute_filter_visibility/views/product_attribute_views.xml
odoo11_addon_website_sale_product_attribute_filter_visibility-11.0.1.0.0.99.dev8.dist-info/METADATA
odoo11_addon_website_sale_product_attribute_filter_visibility-11.0.1.0.0.99.dev8.dist-info/WHEEL
odoo11_addon_website_sale_product_attribute_filter_visibility-11.0.1.0.0.99.dev8.dist-info/top_level.txt
odoo11_addon_website_sale_product_attribute_filter_visibility-11.0.1.0.0.99.dev8.dist-info/RECORD
